<step title="BackgroundTrace" date="2026-05-03T10:06:32.901" instance="e74ad8" url="/api/publish" method="POST" >
  <step title="Creating temporary deployment - FetchDeploymentManager" date="2026-05-03T10:06:33.234" /><!-- duration: 28ms -->
  <step title="Creating temporary deployment" date="2026-05-03T10:06:33.293" /><!-- duration: 261ms -->
  <step title="Performing fetch based deployment" date="2026-05-03T10:06:33.756" >
    <step title="Cleaning up temp folders from previous zip deployments and extracting pushed zip file /tmp/zipdeploy/5436df04-11c4-44e7-a334-ce50d405a15a.zip (0.04 MB) to /tmp/zipdeploy/extracted" date="2026-05-03T10:06:35.305" >
      <step title="ChmodRecursive Process exited with total time taken in ms: 200" date="2026-05-03T10:06:35.659" /><!-- duration: 30ms -->
    </step><!-- duration: 432ms -->
    <step title="Deployment timer started" date="2026-05-03T10:06:37.822" >
      <step title="DeploymentManager.Deploy(id:f36cf63b-059a-4cb4-969b-157f7a55172f)" date="2026-05-03T10:06:37.860" >
        <step title="Collecting changeset information" date="2026-05-03T10:06:37.972" /><!-- duration: 262ms -->
        <step title="Updating submodules" date="2026-05-03T10:06:38.274" /><!-- duration: 1452ms -->
        <step title="Determining deployment builder" date="2026-05-03T10:06:40.867" >
          <step title="Builder is OryxBuilder" date="2026-05-03T10:06:40.904" /><!-- duration: 6ms -->
        </step><!-- duration: 48ms -->
        <step title="PreDeployment: context.CleanOutputPath False" date="2026-05-03T10:06:41.009" >
          <step title="PreDeployment: context.OutputPath /home/site/wwwroot" date="2026-05-03T10:06:41.152" >
            <step title="Building" date="2026-05-03T10:06:41.331" >
              <step title="Executing external process" date="2026-05-03T10:06:41.660" type="process" path="bash" arguments="-c &quot;oryx build /tmp/zipdeploy/extracted -o /home/site/wwwroot --platform python --platform-version 3.11 -p virtualenv_name=antenv --log-file /tmp/build-debug.log  -i /tmp/8dea8fbac039de4 --compress-destination-dir | tee /tmp/oryx-build.log ; exit $PIPESTATUS &quot;" /><!-- duration: 102420ms -->
              <step title="Using PythonDeploymentLogParser" date="2026-05-03T10:08:24.477" /><!-- duration: 4ms -->
              <step title="Modified file to trigger a restart of the app container." date="2026-05-03T10:08:25.920" /><!-- duration: 10ms -->
              <step title="Skip function trigger and logicapp sync because function is not enabled." date="2026-05-03T10:08:25.940" /><!-- duration: 17ms -->
              <step title="Purge deployment items" date="2026-05-03T10:08:27.210" >
                <step title="Remove cb6c5523-, Success, received at 05/03/2026 05:10:09" date="2026-05-03T10:08:27.272" /><!-- duration: 4ms -->
              </step><!-- duration: 71ms -->
            </step><!-- duration: 106042ms -->
          </step><!-- duration: 106226ms -->
          <step title="Cleaning up temp files" date="2026-05-03T10:08:27.383" /><!-- duration: 2870ms -->
          <step title="Cleaning up temp files" date="2026-05-03T10:08:30.260" /><!-- duration: 505ms -->
          <step title="Reloading status file with latest updates" date="2026-05-03T10:08:30.794" >
            <step title="WebHooksManager.PublishEventAsync: PostDeployment" date="2026-05-03T10:08:30.799" /><!-- duration: 48ms -->
          </step><!-- duration: 59ms -->
          <step title="Cleaning up temporary deployment - fetch deployment was successful" date="2026-05-03T10:08:30.889" /><!-- duration: 4ms -->
        </step><!-- duration: 109935ms -->
      </step><!-- duration: 113114ms -->
